mynux/__init__.py
mynux/__main__.py
mynux/cli/__init__.py
mynux/cli/add.py
mynux/cli/info.py
mynux/cli/install.py
mynux/storage/__init__.py
mynux/storage/mynux.py
mynux/storage/plain.py
mynux/storage/remote.py
mynux/system.py
mynux/utils/__init__.py
mynux/utils/action.py
mynux-0.2.1.dist-info/entry_points.txt
mynux-0.2.1.dist-info/WHEEL
mynux-0.2.1.dist-info/METADATA
mynux-0.2.1.dist-info/RECORD
