Metadata-Version: 2.1
Name: mynux
Version: 0.2.1
Summary: 
Author: axju
Author-email: moin@axju.de
Requires-Python: >=3.10,<4.0
Classifier: Programming Language :: Python :: 3
Classifier: Programming Language :: Python :: 3.10
Requires-Dist: tomli (>=2.0.1,<3.0.0); python_version < "3.11"
Requires-Dist: tox (>=3.25.1,<4.0.0)
